wado/__init__.py
wado/wado.py
wado-0.1.1.dist-info/AUTHORS.rst
wado-0.1.1.dist-info/LICENSE
wado-0.1.1.dist-info/METADATA
wado-0.1.1.dist-info/WHEEL
wado-0.1.1.dist-info/top_level.txt
wado-0.1.1.dist-info/RECORD
