Metadata-Version: 2.1
Name: wado
Version: 0.1.1
Summary: Download DICOM images using WADO
Home-page: https://github.com/sjoerdk/wado
Author: Sjoerd Kerkstra
Author-email: sjoerd.kerkstra@radboudumc.nl
License: GNU General Public License v3
Keywords: wado
Platform: UNKNOWN
Classifier: Development Status :: 2 - Pre-Alpha
Classifier: Intended Audience :: Developers
Classifier: License :: OSI Approved :: GNU General Public License v3 (GPLv3)
Classifier: Natural Language :: English
Classifier: Programming Language :: Python :: 3.7
